mseep_zotero_mcp-0.1.10.dist-info/licenses/LICENSE
zotero_mcp/__init__.py
zotero_mcp/cli.py
zotero_mcp/client.py
mseep_zotero_mcp-0.1.10.dist-info/METADATA
mseep_zotero_mcp-0.1.10.dist-info/WHEEL
mseep_zotero_mcp-0.1.10.dist-info/entry_points.txt
mseep_zotero_mcp-0.1.10.dist-info/top_level.txt
mseep_zotero_mcp-0.1.10.dist-info/RECORD
