Metadata-Version: 2.4
Name: mseep-zotero-mcp
Version: 0.1.10
Summary: Model Context Protocol server for Zotero
Author-email: mseep <support@skydeck.ai>
License: MIT License
Project-URL: Repository, https://github.com/kujenga/zotero-mcp
Project-URL: Issues, https://github.com/kujenga/zotero-mcp/issues
Keywords: mcp,zotero
Classifier: Intended Audience :: Developers
Classifier: License :: OSI Approved :: MIT License
Classifier: Programming Language :: Python :: 3.11
Classifier: Programming Language :: Python :: 3.12
Classifier: Programming Language :: Python :: 3.13
Classifier: Programming Language :: Python :: 3 :: Only
Classifier: Operating System :: OS Independent
Requires-Python: >=3.11
License-File: LICENSE
Requires-Dist: mcp[cli]>=1.2.1
Requires-Dist: pydantic>=2.10.6
Requires-Dist: python-dotenv>=1.0.1
Requires-Dist: pyzotero>=1.6.8
Dynamic: license-file
